<annotation>
	<folder>panel_image</folder>
	<filename>25P.jpg</filename>
	<path>/home/liqin/python/panel_image/25P.jpg</path>
	<source>
		<database>Unknown</database>
	</source>
	<size>
		<width>4000</width>
		<height>3000</height>
		<depth>3</depth>
	</size>
	<segmented>0</segmented>
	<object>
		<name>2</name>
		<pose>Unspecified</pose>
		<truncated>0</truncated>
		<difficult>0</difficult>
		<bndbox>
			<xmin>3033</xmin>
			<ymin>1038</ymin>
			<xmax>3175</xmax>
			<ymax>1152</ymax>
		</bndbox>
	</object>
	<object>
		<name>2</name>
		<pose>Unspecified</pose>
		<truncated>0</truncated>
		<difficult>0</difficult>
		<bndbox>
			<xmin>3031</xmin>
			<ymin>1635</ymin>
			<xmax>3171</xmax>
			<ymax>1777</ymax>
		</bndbox>
	</object>
</annotation>
